toolkit/__init__.py
toolkit/types_app.py
toolkit/api/__init__.py
toolkit/api/bot/__init__.py
toolkit/api/bot/utils.py
toolkit/api/fastapi/__init__.py
toolkit/api/fastapi/dependencies.py
toolkit/api/fastapi/exception_handlers.py
toolkit/api/fastapi/responses.py
toolkit/api/fastapi/utils.py
toolkit/auth/__init__.py
toolkit/auth/config.py
toolkit/auth/schemas.py
toolkit/auth/api/dependencies.py
toolkit/auth/api/endpoints.py
toolkit/auth/api/exceptions.py
toolkit/auth/services/password.py
toolkit/auth/services/token.py
toolkit/auth/services/user.py
toolkit/config/__init__.py
toolkit/config/app_config.py
toolkit/config/base.py
toolkit/config/bot_config.py
toolkit/config/cache_config.py
toolkit/config/db_config.py
toolkit/config/testdb_config.py
toolkit/models/__init__.py
toolkit/models/base.py
toolkit/models/log.py
toolkit/models/user.py
toolkit/repo/__init__.py
toolkit/repo/cache/__init__.py
toolkit/repo/cache/crud.py
toolkit/repo/db/__init__.py
toolkit/repo/db/crud.py
toolkit/repo/db/exceptions.py
toolkit/repo/db/messages.py
toolkit/schemas/__init__.py
toolkit/schemas/base.py
toolkit/schemas/log.py
toolkit/schemas/user.py
toolkit/services/db_service.py
toolkit/services/log.py
toolkit/services/service_session_dependent.py
toolkit/services/service_session_independent.py
toolkit/services/user.py
toolkit/test_tools/__init__.py
toolkit/test_tools/base_test_bot.py
toolkit/test_tools/base_test_config.py
toolkit/test_tools/base_test_crud.py
toolkit/test_tools/base_test_fastapi.py
toolkit/test_tools/base_test_model.py
toolkit/test_tools/base_testdata.py
toolkit/test_tools/mixins.py
toolkit/test_tools/utils.py
toolkit/test_tools/fixtures/__init__.py
toolkit/test_tools/fixtures/bot_fixtures.py
toolkit/test_tools/fixtures/fastapi_fixtures.py
toolkit/test_tools/fixtures/general_fixtures.py
toolkit/utils/__init__.py
toolkit/utils/asyncio_utils.py
toolkit/utils/converter.py
toolkit/utils/misc_utils.py
app_toolkit_package-1.0.4.dist-info/METADATA
app_toolkit_package-1.0.4.dist-info/WHEEL
app_toolkit_package-1.0.4.dist-info/top_level.txt
app_toolkit_package-1.0.4.dist-info/RECORD
