Metadata-Version: 2.4
Name: app-toolkit-package
Version: 1.0.4
Requires-Dist: fastapi
Requires-Dist: aiogram
Requires-Dist: pydantic[email]
Requires-Dist: pydantic_core
Requires-Dist: pydantic-settings
Requires-Dist: asyncpg
Requires-Dist: redis
Requires-Dist: SQLAlchemy
Requires-Dist: uvicorn[standard]
Requires-Dist: pyjwt
Requires-Dist: passlib[bcrypt]
Requires-Dist: python-multipart
Provides-Extra: build
Requires-Dist: build; extra == "build"
Requires-Dist: twine; extra == "build"
Provides-Extra: test
Requires-Dist: httpx; extra == "test"
Requires-Dist: pytest; extra == "test"
Requires-Dist: pytest-asyncio; extra == "test"
Requires-Dist: pytest-cov; extra == "test"
